passpro
